<xml xmlns="https://developers.google.com/blockly/xml"><block type="start_flag" id="HeiXv1IU4u,U4(,Am$:7" x="10" y="10"><next><block type="set_drone_LED_junior" id="}E6yA*GPN8%`st7Je;sq"><field name="colour">#ff00ff</field><value name="brightness"><shadow type="limit_0_To_255_255" id="uhB9J~Du)Gh3v|u6.Nb~"><field name="NUM">255</field></shadow></value><next><block type="take_off_senior" id="J]Ni[W7)#YDE;?o;SR):"><next><block type="hover_senior" id="|ETcgzna+hLz~PnwP2i,"><value name="NUM0"><shadow type="math_number" id="pgLd5%5]i`1AE2p,.vhW"><field name="NUM">0.5</field></shadow></value><next><block type="text_print" id="=r@LuzC$%q85+?7dGncj"><value name="TEXT"><block type="get_height_senior" id="MoFm,!f^|BLIcKMQz05`"><field name="UNIT">m</field></block></value><next><block type="text_print" id="-8?2GSbZN[jOol)+Z0~3"><value name="TEXT"><block type="get_pressure_senior" id="BbL/h;MM=sv{{YP;d[}u"><field name="UNIT">pascal</field></block></value><next><block type="controls_repeat_ext" id="eM*-M9`d|Wl.P?N/`|=Y"><value name="TIMES"><shadow type="math_number" id="FiFaAuI4o/3)(C:cF|^_"><field name="NUM">8</field></shadow></value><statement name="DO"><block type="move_senior" id="t$gN7K9B;e}Ahgup}CGH"><value name="ROLL"><shadow type="only_integers_limit_100" id="{.!04;tqr*KTr~VcwsLd"><field name="NUM">0</field></shadow></value><value name="PITCH"><shadow type="only_integers_limit_100" id="cBE]MXfCY8L3mpUwo|n*"><field name="NUM">0</field></shadow></value><value name="YAW"><shadow type="only_integers_limit_100" id="[g|I%gOy!MiU+l77nfRG"><field name="NUM">0</field></shadow></value><value name="THROTTLE"><shadow type="only_integers_limit_100" id="yT4.*(:-m}2k9q2y4wag"><field name="NUM">10</field></shadow></value><value name="NUM0"><shadow type="limit_0_To_100_decimal" id="!kQh.tSskH{:Fd=0E9~x"><field name="NUM">1</field></shadow></value><next><block type="hover_senior" id="]y-LXmf3l8cqGT+v=F3["><value name="NUM0"><shadow type="math_number" id="fLTznx?jTa0j@wu:VZg]"><field name="NUM">0.5</field></shadow></value><next><block type="text_print" id="dAP-5/:JP-+p+raov3mq"><value name="TEXT"><block type="get_height_senior" id="DYr{T_tYYy%tFAP?u7|B"><field name="UNIT">m</field></block></value><next><block type="text_print" id="$nl#a?2zON|*^=:}uQ/+"><value name="TEXT"><block type="get_pressure_senior" id="pIDnIommy=i{=pjU(NoC"><field name="UNIT">pascal</field></block></value></block></next></block></next></block></next></block></statement><next><block type="land_senior" id="pCz?{c[S$+o{yf`awKGV"></block></next></block></next></block></next></block></next></block></next></block></next></block></next></block></xml>